{"filename":"/Users/michaelburke/github/corkandcandles/__azurite_db_blob__.json","collections":[{"name":"$SERVICES_COLLECTION$","data":[],"idIndex":null,"binaryIndices":{},"constraints":null,"uniqueNames":["accountName"],"transforms":{},"objType":"$SERVICES_COLLECTION$","dirty":false,"cachedIndex":null,"cachedBinaryIndex":null,"cachedData":null,"adaptiveBinaryIndices":true,"transactional":false,"cloneObjects":false,"cloneMethod":"parse-stringify","asyncListeners":false,"disableMeta":false,"disableChangesApi":true,"disableDeltaChangesApi":true,"autoupdate":false,"serializableIndices":true,"disableFreeze":true,"ttl":null,"maxId":0,"DynamicViews":[],"events":{"insert":[],"update":[],"pre-insert":[],"pre-update":[],"close":[],"flushbuffer":[],"error":[],"delete":[null],"warning":[null]},"changes":[],"dirtyIds":[]},{"name":"$CONTAINERS_COLLECTION$","data":[{"accountName":"devstoreaccount1","name":"azure-webjobs-hosts","properties":{"etag":"\"0x23B9448C104D760\"","lastModified":"2026-02-20T17:59:23.037Z","leaseStatus":"unlocked","leaseState":"available","hasImmutabilityPolicy":false,"hasLegalHold":false},"meta":{"revision":0,"created":1771610363039,"version":0},"$loki":1}],"idIndex":null,"binaryIndices":{"accountName":{"name":"accountName","dirty":false,"values":[0]},"name":{"name":"name","dirty":false,"values":[0]}},"constraints":null,"uniqueNames":[],"transforms":{},"objType":"$CONTAINERS_COLLECTION$","dirty":false,"cachedIndex":null,"cachedBinaryIndex":null,"cachedData":null,"adaptiveBinaryIndices":true,"transactional":false,"cloneObjects":false,"cloneMethod":"parse-stringify","asyncListeners":false,"disableMeta":false,"disableChangesApi":true,"disableDeltaChangesApi":true,"autoupdate":false,"serializableIndices":true,"disableFreeze":true,"ttl":null,"maxId":1,"DynamicViews":[],"events":{"insert":[],"update":[],"pre-insert":[],"pre-update":[],"close":[],"flushbuffer":[],"error":[],"delete":[null],"warning":[null]},"changes":[],"dirtyIds":[]},{"name":"$BLOBS_COLLECTION$","data":[{"deleted":false,"accountName":"devstoreaccount1","containerName":"azure-webjobs-hosts","name":"locks/mbpro-399539938/Host.Functions.daily_sync.Listener","properties":{"creationTime":"2026-02-20T17:59:23.043Z","lastModified":"2026-02-20T17:59:23.043Z","etag":"\"0x259DDB77218BFC0\"","contentLength":0,"contentType":"application/octet-stream","contentMD5":{"type":"Buffer","data":[212,29,140,217,143,0,178,4,233,128,9,152,236,248,66,126]},"blobType":"BlockBlob","leaseStatus":"locked","leaseState":"leased","serverEncrypted":true,"accessTier":"Hot","accessTierInferred":true,"accessTierChangeTime":"2026-02-20T17:59:23.043Z","leaseDuration":"fixed"},"snapshot":"","isCommitted":true,"persistency":{"id":"08b533a4-b7cb-414a-87c8-dce46e7a263e","offset":0,"count":0},"meta":{"revision":10,"created":1771610363051,"version":0,"updated":1771610430640},"$loki":1,"leaseId":"919b9c76-bdd3-4893-9483-436c9a60837b","leaseExpireTime":"2026-02-20T18:00:45.639Z","leaseDurationSeconds":15},{"deleted":false,"accountName":"devstoreaccount1","containerName":"azure-webjobs-hosts","name":"timers/mbpro-399539938/Host.Functions.daily_sync/status","properties":{"creationTime":"2026-02-20T17:59:23.089Z","lastModified":"2026-02-20T17:59:23.089Z","etag":"\"0x1BA8EDB06DE1770\"","contentLength":120,"contentType":"application/octet-stream","contentMD5":{"type":"Buffer","data":[12,230,157,218,173,67,143,152,71,38,144,162,61,99,222,198]},"blobType":"BlockBlob","leaseStatus":"unlocked","leaseState":"available","serverEncrypted":true,"accessTier":"Hot","accessTierInferred":true,"accessTierChangeTime":"2026-02-20T17:59:23.089Z"},"snapshot":"","isCommitted":true,"persistency":{"id":"08b533a4-b7cb-414a-87c8-dce46e7a263e","offset":0,"count":120},"meta":{"revision":0,"created":1771610363095,"version":0},"$loki":2},{"deleted":false,"metadata":{"FunctionInstance":"000000000000000000000000802AB54C"},"accountName":"devstoreaccount1","containerName":"azure-webjobs-hosts","name":"locks/mbpro-399539938/host","properties":{"creationTime":"2026-02-20T17:59:27.844Z","lastModified":"2026-02-20T17:59:27.873Z","etag":"\"0x24165192A244840\"","contentLength":0,"contentType":"application/octet-stream","contentMD5":{"type":"Buffer","data":[212,29,140,217,143,0,178,4,233,128,9,152,236,248,66,126]},"blobType":"BlockBlob","leaseStatus":"locked","leaseState":"leased","serverEncrypted":true,"accessTier":"Hot","accessTierInferred":true,"accessTierChangeTime":"2026-02-20T17:59:27.844Z","leaseDuration":"fixed"},"snapshot":"","isCommitted":true,"persistency":{"id":"08b533a4-b7cb-414a-87c8-dce46e7a263e","offset":120,"count":0},"meta":{"revision":7,"created":1771610367850,"version":0,"updated":1771610427886},"$loki":3,"leaseId":"000000000000000000000000802AB54C","leaseExpireTime":"2026-02-20T18:00:42.885Z","leaseDurationSeconds":15}],"idIndex":[1,2,3],"binaryIndices":{"accountName":{"name":"accountName","dirty":false,"values":[0,2,1]},"containerName":{"name":"containerName","dirty":false,"values":[0,2,1]},"name":{"name":"name","dirty":false,"values":[0,2,1]},"snapshot":{"name":"snapshot","dirty":false,"values":[0,2,1]}},"constraints":null,"uniqueNames":[],"transforms":{},"objType":"$BLOBS_COLLECTION$","dirty":false,"cachedIndex":null,"cachedBinaryIndex":null,"cachedData":null,"adaptiveBinaryIndices":true,"transactional":false,"cloneObjects":false,"cloneMethod":"parse-stringify","asyncListeners":false,"disableMeta":false,"disableChangesApi":true,"disableDeltaChangesApi":true,"autoupdate":false,"serializableIndices":true,"disableFreeze":true,"ttl":null,"maxId":3,"DynamicViews":[],"events":{"insert":[],"update":[],"pre-insert":[],"pre-update":[],"close":[],"flushbuffer":[],"error":[],"delete":[null],"warning":[null]},"changes":[],"dirtyIds":[]},{"name":"$BLOCKS_COLLECTION$","data":[],"idIndex":null,"binaryIndices":{"accountName":{"name":"accountName","dirty":false,"values":[]},"containerName":{"name":"containerName","dirty":false,"values":[]},"blobName":{"name":"blobName","dirty":false,"values":[]},"name":{"name":"name","dirty":false,"values":[]}},"constraints":null,"uniqueNames":[],"transforms":{},"objType":"$BLOCKS_COLLECTION$","dirty":false,"cachedIndex":null,"cachedBinaryIndex":null,"cachedData":null,"adaptiveBinaryIndices":true,"transactional":false,"cloneObjects":false,"cloneMethod":"parse-stringify","asyncListeners":false,"disableMeta":false,"disableChangesApi":true,"disableDeltaChangesApi":true,"autoupdate":false,"serializableIndices":true,"disableFreeze":true,"ttl":null,"maxId":0,"DynamicViews":[],"events":{"insert":[],"update":[],"pre-insert":[],"pre-update":[],"close":[],"flushbuffer":[],"error":[],"delete":[null],"warning":[null]},"changes":[],"dirtyIds":[]}],"databaseVersion":1.5,"engineVersion":1.5,"autosave":true,"autosaveInterval":5000,"autosaveHandle":null,"throttledSaves":true,"options":{"persistenceMethod":"fs","autosave":true,"autosaveInterval":5000,"serializationMethod":"normal","destructureDelimiter":"$<\n"},"persistenceMethod":"fs","persistenceAdapter":null,"verbose":false,"events":{"init":[null],"loaded":[],"flushChanges":[],"close":[],"changes":[],"warning":[]},"ENV":"NODEJS"}